jfjoch_client/__init__.py
jfjoch_client/api_client.py
jfjoch_client/api_response.py
jfjoch_client/configuration.py
jfjoch_client/exceptions.py
jfjoch_client/py.typed
jfjoch_client/rest.py
jfjoch_client/api/__init__.py
jfjoch_client/api/default_api.py
jfjoch_client/models/__init__.py
jfjoch_client/models/azim_int_settings.py
jfjoch_client/models/broker_status.py
jfjoch_client/models/calibration_statistics_inner.py
jfjoch_client/models/dark_mask_settings.py
jfjoch_client/models/dataset_settings.py
jfjoch_client/models/dataset_settings_xray_fluorescence_spectrum.py
jfjoch_client/models/detector.py
jfjoch_client/models/detector_list.py
jfjoch_client/models/detector_list_element.py
jfjoch_client/models/detector_module.py
jfjoch_client/models/detector_module_direction.py
jfjoch_client/models/detector_power_state.py
jfjoch_client/models/detector_selection.py
jfjoch_client/models/detector_settings.py
jfjoch_client/models/detector_state.py
jfjoch_client/models/detector_status.py
jfjoch_client/models/detector_timing.py
jfjoch_client/models/detector_type.py
jfjoch_client/models/error_message.py
jfjoch_client/models/file_writer_format.py
jfjoch_client/models/file_writer_settings.py
jfjoch_client/models/fpga_status_inner.py
jfjoch_client/models/geom_refinement_algorithm.py
jfjoch_client/models/grid_scan.py
jfjoch_client/models/image_buffer_status.py
jfjoch_client/models/image_format_settings.py
jfjoch_client/models/image_pusher_type.py
jfjoch_client/models/indexing_algorithm.py
jfjoch_client/models/indexing_settings.py
jfjoch_client/models/instrument_metadata.py
jfjoch_client/models/jfjoch_settings.py
jfjoch_client/models/jfjoch_settings_ssl.py
jfjoch_client/models/jfjoch_statistics.py
jfjoch_client/models/measurement_statistics.py
jfjoch_client/models/pcie_devices_inner.py
jfjoch_client/models/pixel_mask_statistics.py
jfjoch_client/models/plot.py
jfjoch_client/models/plot_unit_x.py
jfjoch_client/models/plots.py
jfjoch_client-1.0.0rc124.dist-info/METADATA
jfjoch_client-1.0.0rc124.dist-info/RECORD
jfjoch_client-1.0.0rc124.dist-info/WHEEL
jfjoch_client-1.0.0rc124.dist-info/top_level.txt
