Metadata-Version: 2.1
Name: jfjoch-client
Version: 1.0.0rc124
Summary: Jungfraujoch
Home-page: UNKNOWN
Author: Filip Leonarski (Paul Scherrer Institute)
Author-email: filip.leonarski@psi.ch
License: GPL-3.0
Keywords: OpenAPI,OpenAPI-Generator,Jungfraujoch
Platform: UNKNOWN
Requires-Dist: urllib3 (<2.1.0,>=1.25.3)
Requires-Dist: python-dateutil
Requires-Dist: pydantic (>=2)
Requires-Dist: typing-extensions (>=4.7.1)
